LICENSE
README.md
pyproject.toml
setup.py
plumbline/__init__.py
plumbline/__main__.py
plumbline/plumbline.py
plumbline.egg-info/PKG-INFO
plumbline.egg-info/SOURCES.txt
plumbline.egg-info/dependency_links.txt
plumbline.egg-info/entry_points.txt
plumbline.egg-info/requires.txt
plumbline.egg-info/top_level.txt