Metadata-Version: 2.1
Name: plumbline
Version: 0.0.5
Summary: Python for comparing EPT and DEM data
Home-page: https://github.com/hobu/plumbline
Author: Howard Butler
Author-email: howard@hobu.co
License: UNKNOWN
Platform: UNKNOWN
Classifier: Development Status :: 4 - Beta
Classifier: Intended Audience :: Developers
Classifier: License :: OSI Approved :: MIT License
Classifier: Programming Language :: Python :: 3.8
Requires-Python: >=3.8
License-File: LICENSE
